{"strategy":{"SampleStrategy":{"trades":[{"pair":"BTC/USDT","stake_amount":50,"amount":0.00125263,"open_date":"2022-04-15 00:00:00+00:00","close_date":"2022-04-18 00:00:00+00:00","open_rate":39915.9,"close_rate":39500.857648470315,"fee_open":0.0002,"fee_close":0.0002,"trade_duration":4320,"profit_ratio":0.01019186,"profit_abs":0.50948971,"exit_reason":"roi","initial_stop_loss_abs":77533.8527689243,"initial_stop_loss_ratio":-0.99,"stop_loss_abs":77533.8527689243,"stop_loss_ratio":-0.99,"min_rate":38465.7,"max_rate":42166.8,"is_open":false,"enter_tag":null,"is_short":true,"open_timestamp":1649980800000,"close_timestamp":1650240000000,"orders":[{"amount":0.00125263,"safe_price":39915.9,"ft_order_side":"sell","order_filled_timestamp":1649980800000,"ft_is_entry":true},{"amount":0.00125263,"safe_price":39500.857648470315,"ft_order_side":"buy","order_filled_timestamp":1650240000000,"ft_is_entry":false}]}],"locks":[],"best_pair":{"key":"BTC/USDT","trades":1,"profit_mean":0.01019186,"profit_mean_pct":1.0191860000000001,"profit_sum":0.01019186,"profit_sum_pct":1.02,"profit_total_abs":0.50948971,"profit_total":5.094902194902195e-07,"profit_total_pct":0.0,"duration_avg":"3 days, 0:00:00","wins":1,"draws":0,"losses":0},"worst_pair":{"key":"BTC/USDT","trades":1,"profit_mean":0.01019186,"profit_mean_pct":1.0191860000000001,"profit_sum":0.01019186,"profit_sum_pct":1.02,"profit_total_abs":0.50948971,"profit_total":5.094902194902195e-07,"profit_total_pct":0.0,"duration_avg":"3 days, 0:00:00","wins":1,"draws":0,"losses":0},"results_per_pair":[{"key":"BTC/USDT","trades":1,"profit_mean":0.01019186,"profit_mean_pct":1.0191860000000001,"profit_sum":0.01019186,"profit_sum_pct":1.02,"profit_total_abs":0.50948971,"profit_total":5.094902194902195e-07,"profit_total_pct":0.0,"duration_avg":"3 days, 0:00:00","wins":1,"draws":0,"losses":0},{"key":"TOTAL","trades":1,"profit_mean":0.01019186,"profit_mean_pct":1.0191860000000001,"profit_sum":0.01019186,"profit_sum_pct":1.02,"profit_total_abs":0.50948971,"profit_total":5.094902194902195e-07,"profit_total_pct":0.0,"duration_avg":"3 days, 0:00:00","wins":1,"draws":0,"losses":0}],"results_per_enter_tag":[{"key":"TOTAL","trades":1,"profit_mean":0.01019186,"profit_mean_pct":1.0191860000000001,"profit_sum":0.01019186,"profit_sum_pct":1.02,"profit_total_abs":0.50948971,"profit_total":5.094902194902195e-07,"profit_total_pct":0.0,"duration_avg":"3 days, 0:00:00","wins":1,"draws":0,"losses":0}],"exit_reason_summary":[{"exit_reason":"roi","trades":1,"wins":1,"draws":0,"losses":0,"profit_mean":0.01019186,"profit_mean_pct":1.02,"profit_sum":0.01019186,"profit_sum_pct":1.02,"profit_total_abs":0.50948971,"profit_total":0.01019186,"profit_total_pct":1.02}],"left_open_trades":[{"key":"TOTAL","trades":0,"profit_mean":0.0,"profit_mean_pct":0.0,"profit_sum":0.0,"profit_sum_pct":0.0,"profit_total_abs":0.0,"profit_total":0.0,"profit_total_pct":0.0,"duration_avg":"0:00","wins":0,"draws":0,"losses":0}],"total_trades":1,"trade_count_long":0,"trade_count_short":1,"total_volume":50.0,"avg_stake_amount":50.0,"profit_mean":0.01019186,"profit_median":0.01019186,"profit_total":5.094902194902195e-07,"profit_total_long":0.0,"profit_total_short":5.094902194902195e-07,"profit_total_abs":0.50948971,"profit_total_long_abs":0.0,"profit_total_short_abs":0.50948971,"cagr":6.964941854370466e-07,"profit_factor":0.0,"backtest_start":"2021-10-26 00:00:00","backtest_start_ts":1635206400000,"backtest_end":"2022-07-20 00:00:00","backtest_end_ts":1658275200000,"backtest_days":267,"backtest_run_start_ts":1658946171,"backtest_run_end_ts":1658946172,"trades_per_day":0.0,"market_change":-0.4627167339008252,"pairlist":["BTC/USDT"],"stake_amount":50,"stake_currency":"USDT","stake_currency_decimals":3,"starting_balance":999999.0,"dry_run_wallet":999999.0,"final_balance":999999.50948971,"rejected_signals":0,"timedout_entry_orders":0,"timedout_exit_orders":0,"canceled_trade_entries":0,"canceled_entry_orders":0,"replaced_entry_orders":0,"max_open_trades":1,"max_open_trades_setting":10000,"timeframe":"3d","timeframe_detail":"","timerange":"","enable_protections":false,"strategy_name":"SampleStrategy","stoploss":-0.99,"trailing_stop":false,"trailing_stop_positive":null,"trailing_stop_positive_offset":0.0,"trailing_only_offset_is_reached":false,"use_custom_stoploss":false,"minimal_roi":{"60":0.01,"30":0.02,"0":0.04},"use_exit_signal":false,"exit_profit_only":true,"exit_profit_offset":0.0,"ignore_roi_if_entry_signal":false,"backtest_best_day":0.01019186,"backtest_worst_day":0.01019186,"backtest_best_day_abs":0.50948971,"backtest_worst_day_abs":0.50948971,"winning_days":1,"draw_days":0,"losing_days":0,"daily_profit":[["2022-04-18",0.50948971]],"wins":1,"losses":0,"draws":0,"holding_avg":"3 days, 0:00:00","holding_avg_s":259200.0,"winner_holding_avg":"3 days, 0:00:00","winner_holding_avg_s":259200.0,"loser_holding_avg":"0:00:00","loser_holding_avg_s":0.0,"max_drawdown":0.0,"max_drawdown_account":0.0,"max_relative_drawdown":0.0,"max_drawdown_abs":0.0,"max_drawdown_low":0.0,"max_drawdown_high":0.0,"drawdown_start":"1970-01-01 00:00:00+00:00","drawdown_start_ts":0,"drawdown_end":"1970-01-01 00:00:00+00:00","drawdown_end_ts":0,"csum_min":0,"csum_max":0}},"strategy_comparison":[{"key":"SampleStrategy","trades":1,"profit_mean":0.01019186,"profit_mean_pct":1.0191860000000001,"profit_sum":0.01019186,"profit_sum_pct":1.02,"profit_total_abs":0.50948971,"profit_total":5.094902194902195e-07,"profit_total_pct":0.0,"duration_avg":"3 days, 0:00:00","wins":1,"draws":0,"losses":0,"max_drawdown_account":0.0,"max_drawdown_abs":"0"}]}